pm/__init__.py
pm/db.py
pm/main.py
pm/password.py
yash_password_manager-0.1.dist-info/METADATA
yash_password_manager-0.1.dist-info/WHEEL
yash_password_manager-0.1.dist-info/entry_points.txt
yash_password_manager-0.1.dist-info/top_level.txt
yash_password_manager-0.1.dist-info/RECORD
